froeling_proxy/__init__.py
froeling_proxy/__main__.py
froeling_proxy/froeling_lib.py
froeling_proxy-1.0.0.dist-info/LICENSE
froeling_proxy-1.0.0.dist-info/METADATA
froeling_proxy-1.0.0.dist-info/WHEEL
froeling_proxy-1.0.0.dist-info/top_level.txt
froeling_proxy-1.0.0.dist-info/RECORD
